docxer/__init__.py
docxer-0.0.1b0.dist-info/LICENSE
docxer-0.0.1b0.dist-info/METADATA
docxer-0.0.1b0.dist-info/WHEEL
docxer-0.0.1b0.dist-info/top_level.txt
docxer-0.0.1b0.dist-info/RECORD
