Metadata-Version: 2.1
Name: docxer
Version: 0.0.1b0
Summary: The best way to work with DOCX in Python.
Home-page: https://github.com/ispaneli/docxer
Author: Ilya Antonov
Author-email: ispanelki@gmail.com
Project-URL: Issue Tracker, https://github.com/ispaneli/docxer/issues
Project-URL: Source, https://github.com/ispaneli/docxer/tree/master/src/docxer
Project-URL: Say Thanks!, http://saythanks.io/to/ispanelki
Project-URL: Documentation, https://github.com/ispaneli/docxer
Keywords: docx,document
Classifier: Development Status :: 4 - Beta
Classifier: License :: OSI Approved :: MIT License
Classifier: Operating System :: OS Independent
Classifier: Programming Language :: Python
Classifier: Programming Language :: Python :: 3
Classifier: Programming Language :: Python :: 3 :: Only
Requires-Python: <4,>=3.7
License-File: LICENSE
